{
  "volume": 36,
  "shuffle_mode": false,
  "repeat_mode": false,
  "theme": "AURA Mavi",
  "show_album_art": true,
  "crossfade_duration": 500,
  "vis_mode": "Spektrum Çubukları",
  "vis_favorites": [],
  "vis_auto_cycle": false,
  "lang": "tr",
  "vis_sensitivity": 50,
  "vis_color_intensity": 50,
  "vis_density": 50,
  "use_projectm": false,
  "audio_output_device_index": null,
  "analysis_window_ms": 4000,
  "audio_min_fill_pct": 45,
  "audio_sample_rate": "auto",
  "audio_force_mono": false,
  "audio_output_device_name": "Otomatik seç",
  "audio_format": "auto",
  "crossfade_on_stop": true,
  "crossfade_on_change": true,
  "crossfade_auto": false,
  "fade_out_on_pause": false,
  "fade_out_pause_ms": 250,
  "use_replaygain": false,
  "replaygain_mode": "track",
  "replaygain_pregain": 0.0,
  "replaygain_clipping": true,
  "bar_color": "RGB",
  "bar_style": "solid_with_cap",
  "bar_effect_mode": "ayna",
  "library_auto_scan": false,
  "library_watch": false,
  "library_paths": [],
  "proxy_enabled": false,
  "proxy_host": "",
  "proxy_port": 0,
  "proxy_user": "",
  "proxy_pass": "",
  "radio_enabled": true,
  "podcast_enabled": false,
  "scrobble_enabled": false,
  "transcode_profile": "MP3 320k",
  "transcode_output_dir": "",
  "soft_stop_crossfade": true,
  "manual_crossfade": true,
  "auto_crossfade": true,
  "exclude_same_album_crossfade": true,
  "pause_fade_enabled": false,
  "pause_fade_duration": 350,
  "replaygain_enabled": false,
  "preamp_db": 0,
  "limiter_enabled": false,
  "audio_output_device": "auto",
  "prebuffer_ms": 4000,
  "min_buffer_fill": 40,
  "sample_rate": "auto",
  "output_format": "detect",
  "mono_playback": false,
  "remember_last": true,
  "show_tray_icon": true,
  "scroll_change_track": false,
  "background_playback": true,
  "warn_close_playlist_tab": false,
  "startup_window_state": "remember",
  "inline_metadata_edit": false,
  "resume_on_start": false,
  "stop_if_fail": false,
  "gray_missing_tracks": false,
  "menu_add_behavior": "play_if_idle",
  "prev_action": "jump",
  "doubleclick_library_action": "add_to_playlist",
  "doubleclick_playlist_action": "play",
  "time_step_seconds": 10,
  "playlist_path_mode": "auto",
  "write_metadata": true,
  "ignore_prefix": true,
  "prefix_words": "a, the",
  "playcount_mode": "normal",
  "library_update_on_start": true,
  "library_watch_changes": false,
  "library_save_ratings": true,
  "library_skip_ext": "",
  "library_cover_names": "front,cover",
  "library_auto_expand_single": true,
  "library_show_cover": true,
  "library_show_dividers": true,
  "metadata_processes": 8,
  "metadata_guess_missing": true,
  "shortcuts": {
    "play_pause": "Space",
    "next_track": "Ctrl+Right",
    "prev_track": "Ctrl+Left",
    "next_track_alt": "F2",
    "prev_track_alt": "F1",
    "seek_back": "F3",
    "seek_forward": "F4",
    "add_files": "Ctrl+O",
    "add_folder": "Ctrl+F",
    "toggle_visualizer": "Ctrl+V",
    "open_preferences": "Ctrl+,",
    "open_about": "Ctrl+H",
    "shuffle": "Ctrl+Shift+S",
    "repeat": "Ctrl+Shift+R",
    "play_selected": "Return",
    "volume_up": "Up",
    "volume_down": "Down",
    "toggle_mute": "M"
  },
  "video_quality": "Auto",
  "autoplay_enabled": false,
  "cinema_mode": false,
  "eq_enabled": false,
  "eq_gains": [
    0.0,
    0.0,
    0.0,
    0.0,
    0.0,
    0.0,
    0.0,
    0.0,
    0.0,
    0.0,
    0.0,
    0.0,
    0.0,
    0.0,
    0.0,
    0.0,
    0.0,
    0.0,
    0.0,
    0.0,
    0.0,
    0.0,
    0.0,
    0.0,
    0.0,
    0.0,
    0.0,
    0.0,
    0.0,
    0.0,
    0.0,
    0.0
  ],
  "effects_input_gain_db": -12.0,
  "effects_output_gain_db": 0.0,
  "effects_bass_enabled": false,
  "effects_bass_gain_db": 0.0,
  "effects_bass_freq_hz": 120.0,
  "effects_limiter_enabled": false,
  "effects_limiter_thresh_db": -1.0,
  "effects_enabled": false,
  "effects_comp_enabled": false,
  "effects_comp_threshold_db": -12.0,
  "effects_comp_ratio": 2.0,
  "effects_comp_attack_ms": 10.0,
  "effects_comp_release_ms": 80.0,
  "effects_comp_makeup_db": 0.0,
  "effects_output_device": "default",
  "effects_bass_threshold_db": 0.0,
  "effects_bass_link": 0.0,
  "effects_bass_enh_enabled": false,
  "effects_bass_enh_amount_db": 0.0,
  "effects_bass_enh_harmonics": 0.0,
  "effects_bass_enh_scope_hz": 0.0,
  "effects_bass_enh_floor_hz": 0.0,
  "effects_bass_enh_floor_active": false,
  "active_effect_keys": [
    "eq",
    "dyn"
  ],
  "effects_low_shelf_db": 0.0,
  "effects_high_shelf_db": 0.0,
  "effects_stereo_width_pct": 100,
  "effects_reverb_preset": "kapalı",
  "effects_poweramp_enabled": false,
  "effects_mid_shelf_db": 0.0,
  "effects_window_size": [
    1494,
    820
  ],
  "effects_window_pos": [
    0,
    0
  ],
  "dynproc_threshold_db": -18.0,
  "dynproc_ratio": 2.0,
  "dynproc_attack_ms": 10,
  "dynproc_width_pct": 100,
  "dynproc_ceiling_db": -1.0,
  "custom_eq_backup": [
    0,
    0,
    0,
    0,
    0,
    0,
    0,
    0,
    0,
    0,
    0,
    0,
    0,
    0,
    0,
    0,
    0,
    0,
    0,
    0,
    0,
    0,
    0,
    0,
    0,
    0,
    0,
    0,
    0,
    0,
    0,
    0
  ],
  "auto_eq_active": false,
  "auto_eq_profile": "",
  "auto_eq_headroom_db": 0.0,
  "auto_eq_gains": [],
  "crossfade_enabled": 2,
  "crossfade_duration_ms": 500,
  "crossfade_manual_enabled": true,
  "crossfade_auto_enabled": false,
  "pause_fade_ms": 2000,
  "manual_crossfade_ms": 3000,
  "crossfade_mode": "equal_power",
  "crossfade_curve": "equal_power",
  "mini_visual_enabled": false,
  "mini_bar_color": "SPECTRUM",
  "mini_bar_style": "outline",
  "visualizer_safe_mode": false,
  "hw_accel": true,
  "auto_start_last": false,
  "replay_gain": false,
  "gapless": true,
  "theme_style": "preset",
  "theme_mode": "dark",
  "theme_accent": "Mavi",
  "playback_rate": 1.0,
  "pitch_stable": false,
  "replaygain_preamp_db": 0.0,
  "replaygain_clip_protect": true,
  "vis_speed": 1.0,
  "cleanup_legacy_bak": false
}